eeg_networks/__init__.py
eeg_networks/dataset.py
eeg_networks/nets/__init__.py
eeg_networks/nets/eeg_inception.py
eeg_networks/nets/eeg_lstm.py
EEGNetworks-0.1.1.dist-info/WHEEL
EEGNetworks-0.1.1.dist-info/METADATA
EEGNetworks-0.1.1.dist-info/RECORD
