Metadata-Version: 2.1
Name: EEGNetworks
Version: 0.1.1
Summary: 基于PyTorch的各种用于EEG分类任务的简单网络的实现。
License: MIT
Author-email: 六个骨头 <2742392377@qq.com>
Requires-Python: >=3.8
Requires-Dist: h5py
Requires-Dist: numpy
Requires-Dist: torch
Requires-Dist: tqdm
Requires-Dist: typer
